{
  "name": "rdft-He-PBE0-DH-energy.log",
  "validation": [
    {
      "header": "WAVEFUNCTION PROPERTIES",
      "name": "WAVEFUNCTION NORMALIZATION",
      "value": "1.0000000000",
      "type": "float",
      "precision": 10,
      "tolerance": 7.5e-07
    },
    {
      "header": "WAVEFUNCTION PROPERTIES",
      "name": "ONE ELECTRON ENERGY",
      "value": "-3.8651431814",
      "type": "float",
      "precision": 10,
      "tolerance": 7.5e-07
    },
    {
      "header": "WAVEFUNCTION PROPERTIES",
      "name": "TWO ELECTRON ENERGY",
      "value": "0.9996030050",
      "type": "float",
      "precision": 10,
      "tolerance": 7.5e-07
    },
    {
      "header": "WAVEFUNCTION PROPERTIES",
      "name": "NUCLEAR REPULSION ENERGY",
      "value": "0.0000000000",
      "type": "float",
      "precision": 10,
      "tolerance": 7.5e-07
    },
    {
      "header": "WAVEFUNCTION PROPERTIES",
      "name": "TOTAL ENERGY",
      "value": "-2.8655401765",
      "type": "float",
      "precision": 10,
      "tolerance": 7.5e-07
    },
    {
      "header": "WAVEFUNCTION PROPERTIES",
      "name": "NUCLEUS-NUCLEUS POTENTIAL ENERGY",
      "value": "0.0000000000",
      "type": "float",
      "precision": 10,
      "tolerance": 7.5e-07
    },
    {
      "header": "WAVEFUNCTION PROPERTIES",
      "name": "ELECTRON-ELECTRON POTENTIAL ENERGY",
      "value": "0.9996030050",
      "type": "float",
      "precision": 10,
      "tolerance": 7.5e-07
    },
    {
      "header": "WAVEFUNCTION PROPERTIES",
      "name": "NUCLEUS-ELECTRON POTENTIAL ENERGY",
      "value": "-6.7062148201",
      "type": "float",
      "precision": 10,
      "tolerance": 7.5e-07
    },
    {
      "header": "WAVEFUNCTION PROPERTIES",
      "name": "TOTAL POTENTIAL ENERGY",
      "value": "-5.7066118151",
      "type": "float",
      "precision": 10,
      "tolerance": 7.5e-07
    },
    {
      "header": "WAVEFUNCTION PROPERTIES",
      "name": "TOTAL KINETIC ENERGY",
      "value": "2.8410716387",
      "type": "float",
      "precision": 10,
      "tolerance": 7.5e-07
    },
    {
      "header": "WAVEFUNCTION PROPERTIES",
      "name": "VIRIAL RATIO (V/T)",
      "value": "2.0086124325",
      "type": "float",
      "precision": 10,
      "tolerance": 7.5e-07
    },
    {
      "header": "MP2",
      "name": "E(SCF)",
      "value": "-2.8655401765",
      "type": "float",
      "precision": 10,
      "tolerance": 7.5e-07
    },
    {
      "header": "MP2",
      "name": "E(2)",
      "value": "-0.0131427118",
      "type": "float",
      "precision": 10,
      "tolerance": 7.5e-07
    },
    {
      "header": "MP2",
      "name": "E(MP2)",
      "value": "-2.8786828883",
      "type": "float",
      "precision": 10,
      "tolerance": 7.5e-07
    },
    {
      "header": "MP2 : SPIN-COMPONENT-SCALED",
      "name": "E(2S)",
      "value": "-0.0131427118",
      "type": "float",
      "precision": 10,
      "tolerance": 7.5e-07
    },
    {
      "header": "MP2 : SPIN-COMPONENT-SCALED",
      "name": "E(2T)",
      "value": "0.0000000000",
      "type": "float",
      "precision": 10,
      "tolerance": 7.5e-07
    },
    {
      "header": "MP2 : SPIN-COMPONENT-SCALED",
      "name": "E(2ST)",
      "value": "-0.0157712542",
      "type": "float",
      "precision": 10,
      "tolerance": 7.5e-07
    },
    {
      "header": "MP2 : SPIN-COMPONENT-SCALED",
      "name": "E(SCS-MP2)",
      "value": "-2.8813114307",
      "type": "float",
      "precision": 10,
      "tolerance": 7.5e-07
    },
    {
      "header": "ELECTROSTATICS",
      "name": "DIPOLE MOMENT",
      "value": "0.000000",
      "type": "float",
      "precision": 6,
      "tolerance": 0.0005
    },
    {
      "header": "TOTAL WALLTIME",
      "name": "TOTAL WALLTIME (S)",
      "value": "0.0",
      "type": "skip_float",
      "precision": 1
    }
  ]
}
