{
  "name": "udft-CN-HCTH-P76-gradient.log",
  "validation": [
    {
      "header": "WAVEFUNCTION PROPERTIES",
      "name": "WAVEFUNCTION NORMALIZATION",
      "value": "1.0000000000",
      "type": "float",
      "precision": 10,
      "tolerance": 7.5e-07
    },
    {
      "header": "WAVEFUNCTION PROPERTIES",
      "name": "ONE ELECTRON ENERGY",
      "value": "-161.2412670755",
      "type": "float",
      "precision": 10,
      "tolerance": 7.5e-07
    },
    {
      "header": "WAVEFUNCTION PROPERTIES",
      "name": "TWO ELECTRON ENERGY",
      "value": "51.7640878412",
      "type": "float",
      "precision": 10,
      "tolerance": 7.5e-07
    },
    {
      "header": "WAVEFUNCTION PROPERTIES",
      "name": "NUCLEAR REPULSION ENERGY",
      "value": "18.9961063830",
      "type": "float",
      "precision": 10,
      "tolerance": 7.5e-07
    },
    {
      "header": "WAVEFUNCTION PROPERTIES",
      "name": "TOTAL ENERGY",
      "value": "-90.4810728513",
      "type": "float",
      "precision": 10,
      "tolerance": 7.5e-07
    },
    {
      "header": "WAVEFUNCTION PROPERTIES",
      "name": "NUCLEUS-NUCLEUS POTENTIAL ENERGY",
      "value": "18.9961063830",
      "type": "float",
      "precision": 10,
      "tolerance": 7.5e-07
    },
    {
      "header": "WAVEFUNCTION PROPERTIES",
      "name": "ELECTRON-ELECTRON POTENTIAL ENERGY",
      "value": "51.7640878412",
      "type": "float",
      "precision": 10,
      "tolerance": 7.5e-07
    },
    {
      "header": "WAVEFUNCTION PROPERTIES",
      "name": "NUCLEUS-ELECTRON POTENTIAL ENERGY",
      "value": "-252.5554455489",
      "type": "float",
      "precision": 10,
      "tolerance": 7.5e-07
    },
    {
      "header": "WAVEFUNCTION PROPERTIES",
      "name": "TOTAL POTENTIAL ENERGY",
      "value": "-181.7952513247",
      "type": "float",
      "precision": 10,
      "tolerance": 7.5e-07
    },
    {
      "header": "WAVEFUNCTION PROPERTIES",
      "name": "TOTAL KINETIC ENERGY",
      "value": "91.3141784734",
      "type": "float",
      "precision": 10,
      "tolerance": 7.5e-07
    },
    {
      "header": "WAVEFUNCTION PROPERTIES",
      "name": "VIRIAL RATIO (V/T)",
      "value": "1.9908764922",
      "type": "float",
      "precision": 10,
      "tolerance": 7.5e-07
    },
    {
      "header": "SELF-CONSISTENT FIELD ENERGY",
      "name": "FINAL SCF ENERGY",
      "value": "-90.4810728513",
      "type": "float",
      "precision": 10,
      "tolerance": 7.5e-07
    },
    {
      "header": "GRADIENT",
      "name": "MAXIMUM GRADIENT",
      "value": "0.071951075",
      "type": "float",
      "precision": 7,
      "tolerance": 5e-05
    },
    {
      "header": "GRADIENT",
      "name": "RMS GRADIENT",
      "value": "0.041540972",
      "type": "float",
      "precision": 7,
      "tolerance": 5e-05
    },
    {
      "header": "SPIN",
      "name": "S-SQUARED",
      "value": "0.763",
      "type": "float",
      "precision": 3,
      "tolerance": 0.5
    },
    {
      "header": "ELECTROSTATICS",
      "name": "DIPOLE MOMENT",
      "value": "1.015605",
      "type": "float",
      "precision": 6,
      "tolerance": 0.0005
    }
  ]
}